{
  "collection": {
    "_": {
      "postman_id": "7574a522-714e-41c6-a22d-8682669221f7",
      "exporter_id": "50807239",
      "collection_link": "https://go.postman.co/collection/50807239-7574a522-714e-41c6-a22d-8682669221f7?source=collection_link"
    },
    "item": [
      {
        "id": "b797491f-99d5-4817-a15d-ad831af6023f",
        "name": "1-GetAllUsers",
        "request": {
          "url": {
            "protocol": "https",
            "path": [
              "public",
              "v2",
              "users"
            ],
            "host": [
              "gorest",
              "co",
              "in"
            ],
            "query": [],
            "variable": []
          },
          "method": "GET"
        },
        "response": [],
        "event": [
          {
            "listen": "test",
            "script": {
              "id": "be857fda-b0ff-41a8-9fcb-f3712d9a47d0",
              "type": "text/javascript",
              "packages": {},
              "exec": [
                "pm.test(\"Status code is 200\", function () {",
                "    pm.response.to.have.status(200);",
                "});",
                "pm.test(\"Response time is less than 200ms\", function () {",
                "    pm.expect(pm.response.responseTime).to.be.below(1000);",
                "});"
              ],
              "_lastExecutionId": "e145b559-052b-42b6-8afb-a5646becb7b8"
            }
          }
        ]
      },
      {
        "id": "7e6a3dbc-887f-49c9-925d-6a3054c15f59",
        "name": "2-GetAUserByID",
        "request": {
          "url": {
            "protocol": "https",
            "path": [
              "public",
              "v2",
              "users",
              "8333165"
            ],
            "host": [
              "gorest",
              "co",
              "in"
            ],
            "query": [],
            "variable": []
          },
          "method": "GET"
        },
        "response": [],
        "event": [
          {
            "listen": "test",
            "script": {
              "id": "1684e710-4821-4314-805d-1d815c5787ba",
              "type": "text/javascript",
              "packages": {},
              "exec": [
                "pm.test(\"Status code is 200\", function () {",
                "    pm.response.to.have.status(200);",
                "});",
                "pm.test(\"Response time is less than 200ms\", function () {",
                "    pm.expect(pm.response.responseTime).to.be.below(1000);",
                "});"
              ],
              "_lastExecutionId": "5353e50c-61db-4b98-972a-791cedcfe60c"
            }
          }
        ]
      }
    ],
    "event": [],
    "variable": [],
    "info": {
      "_postman_id": "7574a522-714e-41c6-a22d-8682669221f7",
      "name": "SimpleCollection",
      "schema": "https://schema.getpostman.com/json/collection/v2.1.0/collection.json"
    }
  },
  "environment": {
    "id": "51d859f0-b172-4ae1-8b40-31049ad9f431",
    "values": []
  },
  "globals": {
    "id": "5ed1b269-48d0-44f1-9f17-bfbbc10bed29",
    "values": []
  },
  "run": {
    "stats": {
      "iterations": {
        "total": 1,
        "pending": 0,
        "failed": 0
      },
      "items": {
        "total": 2,
        "pending": 0,
        "failed": 0
      },
      "scripts": {
        "total": 2,
        "pending": 0,
        "failed": 0
      },
      "prerequests": {
        "total": 2,
        "pending": 0,
        "failed": 0
      },
      "requests": {
        "total": 2,
        "pending": 0,
        "failed": 0
      },
      "tests": {
        "total": 2,
        "pending": 0,
        "failed": 0
      },
      "assertions": {
        "total": 4,
        "pending": 0,
        "failed": 1
      },
      "testScripts": {
        "total": 2,
        "pending": 0,
        "failed": 0
      },
      "prerequestScripts": {
        "total": 0,
        "pending": 0,
        "failed": 0
      }
    },
    "timings": {
      "responseAverage": 713,
      "responseMin": 363,
      "responseMax": 1063,
      "responseSd": 350,
      "dnsAverage": 0,
      "dnsMin": 0,
      "dnsMax": 0,
      "dnsSd": 0,
      "firstByteAverage": 0,
      "firstByteMin": 0,
      "firstByteMax": 0,
      "firstByteSd": 0,
      "started": 1768653238812,
      "completed": 1768653240299
    },
    "executions": [
      {
        "cursor": {
          "position": 0,
          "iteration": 0,
          "length": 2,
          "cycles": 1,
          "empty": false,
          "eof": false,
          "bof": true,
          "cr": false,
          "ref": "439a03cb-bb68-411d-a3d5-12c089f73751",
          "httpRequestId": "22625b35-ffa2-4322-a131-cc62ebd26f80"
        },
        "item": {
          "id": "b797491f-99d5-4817-a15d-ad831af6023f",
          "name": "1-GetAllUsers",
          "request": {
            "url": {
              "protocol": "https",
              "path": [
                "public",
                "v2",
                "users"
              ],
              "host": [
                "gorest",
                "co",
                "in"
              ],
              "query": [],
              "variable": []
            },
            "method": "GET"
          },
          "response": [],
          "event": [
            {
              "listen": "test",
              "script": {
                "id": "be857fda-b0ff-41a8-9fcb-f3712d9a47d0",
                "type": "text/javascript",
                "packages": {},
                "exec": [
                  "pm.test(\"Status code is 200\", function () {",
                  "    pm.response.to.have.status(200);",
                  "});",
                  "pm.test(\"Response time is less than 200ms\", function () {",
                  "    pm.expect(pm.response.responseTime).to.be.below(1000);",
                  "});"
                ],
                "_lastExecutionId": "e145b559-052b-42b6-8afb-a5646becb7b8"
              }
            }
          ]
        },
        "request": {
          "url": {
            "protocol": "https",
            "path": [
              "public",
              "v2",
              "users"
            ],
            "host": [
              "gorest",
              "co",
              "in"
            ],
            "query": [],
            "variable": []
          },
          "header": [
            {
              "key": "User-Agent",
              "value": "PostmanRuntime/7.39.1",
              "system": true
            },
            {
              "key": "Accept",
              "value": "*/*",
              "system": true
            },
            {
              "key": "Cache-Control",
              "value": "no-cache",
              "system": true
            },
            {
              "key": "Postman-Token",
              "value": "5221b141-38c2-4be6-9524-b738ca154a69",
              "system": true
            },
            {
              "key": "Host",
              "value": "gorest.co.in",
              "system": true
            },
            {
              "key": "Accept-Encoding",
              "value": "gzip, deflate, br",
              "system": true
            },
            {
              "key": "Connection",
              "value": "keep-alive",
              "system": true
            }
          ],
          "method": "GET"
        },
        "response": {
          "id": "6d7ca292-cbbd-4ac3-8dee-ecfa1ad062f1",
          "status": "OK",
          "code": 200,
          "header": [
            {
              "key": "Date",
              "value": "Sat, 17 Jan 2026 12:33:59 GMT"
            },
            {
              "key": "Content-Type",
              "value": "application/json; charset=utf-8"
            },
            {
              "key": "Transfer-Encoding",
              "value": "chunked"
            },
            {
              "key": "Connection",
              "value": "keep-alive"
            },
            {
              "key": "Cache-Control",
              "value": "max-age=0, private, must-revalidate"
            },
            {
              "key": "etag",
              "value": "W/\"8a0fe395da357fa2f3f47172084c6648\""
            },
            {
              "key": "feature-policy",
              "value": "camera 'none'; gyroscope 'none'; microphone 'none'; usb 'none'; fullscreen 'self'"
            },
            {
              "key": "referrer-policy",
              "value": "strict-origin-when-cross-origin"
            },
            {
              "key": "vary",
              "value": "Origin"
            },
            {
              "key": "x-content-type-options",
              "value": "nosniff"
            },
            {
              "key": "x-download-options",
              "value": "noopen"
            },
            {
              "key": "x-frame-options",
              "value": "SAMEORIGIN"
            },
            {
              "key": "x-links-current",
              "value": "https://gorest.co.in/public/v2/users?page=1"
            },
            {
              "key": "x-links-next",
              "value": "https://gorest.co.in/public/v2/users?page=2"
            },
            {
              "key": "x-links-previous",
              "value": ""
            },
            {
              "key": "x-pagination-limit",
              "value": "10"
            },
            {
              "key": "x-pagination-page",
              "value": "1"
            },
            {
              "key": "x-pagination-pages",
              "value": "296"
            },
            {
              "key": "x-pagination-total",
              "value": "2952"
            },
            {
              "key": "x-permitted-cross-domain-policies",
              "value": "none"
            },
            {
              "key": "x-request-id",
              "value": "ef9e5160-4c4c-4d30-8dd6-f6d0a1f7b49c"
            },
            {
              "key": "x-runtime",
              "value": "0.021024"
            },
            {
              "key": "x-xss-protection",
              "value": "0"
            },
            {
              "key": "Nel",
              "value": "{\"report_to\":\"cf-nel\",\"success_fraction\":0.0,\"max_age\":604800}"
            },
            {
              "key": "cf-cache-status",
              "value": "DYNAMIC"
            },
            {
              "key": "Report-To",
              "value": "{\"group\":\"cf-nel\",\"max_age\":604800,\"endpoints\":[{\"url\":\"https://a.nel.cloudflare.com/report/v4?s=8SHyFHxnu3Lj2udoI7Cy6%2Fh1roM821JlORpo62ByOIzMqpJNKST%2B2nSsmb1ePCDIndVkcWc0llneO%2Blw%2Ffr1qV2ZQTq%2FhUqY4YY%3D\"}]}"
            },
            {
              "key": "Content-Encoding",
              "value": "br"
            },
            {
              "key": "Server",
              "value": "cloudflare"
            },
            {
              "key": "CF-RAY",
              "value": "9bf5e2579ad242d9-PHX"
            },
            {
              "key": "alt-svc",
              "value": "h3=\":443\"; ma=86400"
            }
          ],
          "stream": {
            "type": "Buffer",
            "data": [
              91,
              123,
              34,
              105,
              100,
              34,
              58,
              56,
              51,
              51,
              51,
              49,
              54,
              53,
              44,
              34,
              110,
              97,
              109,
              101,
              34,
              58,
              34,
              66,
              104,
              97,
              114,
              100,
              119,
              97,
              106,
              32,
              65,
              100,
              105,
              103,
              97,
              34,
              44,
              34,
              101,
              109,
              97,
              105,
              108,
              34,
              58,
              34,
              98,
              104,
              97,
              114,
              100,
              119,
              97,
              106,
              95,
              97,
              100,
              105,
              103,
              97,
              64,
              119,
              97,
              108,
              116,
              101,
              114,
              46,
              116,
              101,
              115,
              116,
              34,
              44,
              34,
              103,
              101,
              110,
              100,
              101,
              114,
              34,
              58,
              34,
              109,
              97,
              108,
              101,
              34,
              44,
              34,
              115,
              116,
              97,
              116,
              117,
              115,
              34,
              58,
              34,
              97,
              99,
              116,
              105,
              118,
              101,
              34,
              125,
              44,
              123,
              34,
              105,
              100,
              34,
              58,
              56,
              51,
              51,
              51,
              49,
              54,
              52,
              44,
              34,
              110,
              97,
              109,
              101,
              34,
              58,
              34,
              66,
              97,
              97,
              108,
              97,
              97,
              100,
              105,
              116,
              121,
              97,
              32,
              83,
              101,
              116,
              104,
              105,
              34,
              44,
              34,
              101,
              109,
              97,
              105,
              108,
              34,
              58,
              34,
              115,
              101,
              116,
              104,
              105,
              95,
              98,
              97,
              97,
              108,
              97,
              97,
              100,
              105,
              116,
              121,
              97,
              64,
              114,
              111,
              109,
              97,
              103,
              117,
              101,
              114,
              97,
              46,
              101,
              120,
              97,
              109,
              112,
              108,
              101,
              34,
              44,
              34,
              103,
              101,
              110,
              100,
              101,
              114,
              34,
              58,
              34,
              102,
              101,
              109,
              97,
              108,
              101,
              34,
              44,
              34,
              115,
              116,
              97,
              116,
              117,
              115,
              34,
              58,
              34,
              105,
              110,
              97,
              99,
              116,
              105,
              118,
              101,
              34,
              125,
              44,
              123,
              34,
              105,
              100,
              34,
              58,
              56,
              51,
              51,
              51,
              49,
              54,
              51,
              44,
              34,
              110,
              97,
              109,
              101,
              34,
              58,
              34,
              67,
              104,
              97,
              110,
              100,
              97,
              32,
              80,
              97,
              116,
              101,
              108,
              34,
              44,
              34,
              101,
              109,
              97,
              105,
              108,
              34,
              58,
              34,
              99,
              104,
              97,
              110,
              100,
              97,
              95,
              112,
              97,
              116,
              101,
              108,
              64,
              104,
              105,
              114,
              116,
              104,
              101,
              46,
              116,
              101,
              115,
              116,
              34,
              44,
              34,
              103,
              101,
              110,
              100,
              101,
              114,
              34,
              58,
              34,
              109,
              97,
              108,
              101,
              34,
              44,
              34,
              115,
              116,
              97,
              116,
              117,
              115,
              34,
              58,
              34,
              97,
              99,
              116,
              105,
              118,
              101,
              34,
              125,
              44,
              123,
              34,
              105,
              100,
              34,
              58,
              56,
              51,
              51,
              51,
              49,
              54,
              50,
              44,
              34,
              110,
              97,
              109,
              101,
              34,
              58,
              34,
              84,
              104,
              101,
              32,
              72,
              111,
              110,
              46,
              32,
              68,
              119,
              97,
              105,
              112,
              97,
              121,
              97,
              110,
              32,
              75,
              97,
              117,
              114,
              34,
              44,
              34,
              101,
              109,
              97,
              105,
              108,
              34,
              58,
              34,
              107,
              97,
              117,
              114,
              95,
              100,
              119,
              97,
              105,
              112,
              97,
              121,
              97,
              110,
              95,
              104,
              111,
              110,
              95,
              116,
              104,
              101,
              64,
              116,
              117,
              114,
              110,
              101,
              114,
              46,
              101,
              120,
              97,
              109,
              112,
              108,
              101,
              34,
              44,
              34,
              103,
              101,
              110,
              100,
              101,
              114,
              34,
              58,
              34,
              109,
              97,
              108,
              101,
              34,
              44,
              34,
              115,
              116,
              97,
              116,
              117,
              115,
              34,
              58,
              34,
              105,
              110,
              97,
              99,
              116,
              105,
              118,
              101,
              34,
              125,
              44,
              123,
              34,
              105,
              100,
              34,
              58,
              56,
              51,
              51,
              51,
              49,
              54,
              49,
              44,
              34,
              110,
              97,
              109,
              101,
              34,
              58,
              34,
              68,
              105,
              118,
              97,
              97,
              107,
              97,
              114,
              32,
              68,
              119,
              105,
              118,
              101,
              100,
              105,
              32,
              69,
              115,
              113,
              46,
              34,
              44,
              34,
              101,
              109,
              97,
              105,
              108,
              34,
              58,
              34,
              100,
              119,
              105,
              118,
              101,
              100,
              105,
              95,
              101,
              115,
              113,
              95,
              100,
              105,
              118,
              97,
              97,
              107,
              97,
              114,
              64,
              97,
              114,
              109,
              115,
              116,
              114,
              111,
              110,
              103,
              46,
              101,
              120,
              97,
              109,
              112,
              108,
              101,
              34,
              44,
              34,
              103,
              101,
              110,
              100,
              101,
              114,
              34,
              58,
              34,
              109,
              97,
              108,
              101,
              34,
              44,
              34,
              115,
              116,
              97,
              116,
              117,
              115,
              34,
              58,
              34,
              97,
              99,
              116,
              105,
              118,
              101,
              34,
              125,
              44,
              123,
              34,
              105,
              100,
              34,
              58,
              56,
              51,
              51,
              51,
              49,
              54,
              48,
              44,
              34,
              110,
              97,
              109,
              101,
              34,
              58,
              34,
              78,
              105,
              109,
              105,
              116,
              32,
              86,
              101,
              114,
              109,
              97,
              34,
              44,
              34,
              101,
              109,
              97,
              105,
              108,
              34,
              58,
              34,
              110,
              105,
              109,
              105,
              116,
              95,
              118,
              101,
              114,
              109,
              97,
              64,
              110,
              105,
              116,
              122,
              115,
              99,
              104,
              101,
              46,
              101,
              120,
              97,
              109,
              112,
              108,
              101,
              34,
              44,
              34,
              103,
              101,
              110,
              100,
              101,
              114,
              34,
              58,
              34,
              102,
              101,
              109,
              97,
              108,
              101,
              34,
              44,
              34,
              115,
              116,
              97,
              116,
              117,
              115,
              34,
              58,
              34,
              97,
              99,
              116,
              105,
              118,
              101,
              34,
              125,
              44,
              123,
              34,
              105,
              100,
              34,
              58,
              56,
              51,
              51,
              51,
              49,
              53,
              57,
              44,
              34,
              110,
              97,
              109,
              101,
              34,
              58,
              34,
              82,
              101,
              112,
              46,
              32,
              68,
              97,
              107,
              115,
              104,
              97,
              121,
              97,
              110,
              105,
              32,
              75,
              97,
              107,
              107,
              97,
              114,
              34,
              44,
              34,
              101,
              109,
              97,
              105,
              108,
              34,
              58,
              34,
              100,
              97,
              107,
              115,
              104,
              97,
              121,
              97,
              110,
              105,
              95,
              107,
              97,
              107,
              107,
              97,
              114,
              95,
              114,
              101,
              112,
              64,
              98,
              97,
              116,
              122,
              46,
              101,
              120,
              97,
              109,
              112,
              108,
              101,
              34,
              44,
              34,
              103,
              101,
              110,
              100,
              101,
              114,
              34,
              58,
              34,
              102,
              101,
              109,
              97,
              108,
              101,
              34,
              44,
              34,
              115,
              116,
              97,
              116,
              117,
              115,
              34,
              58,
              34,
              97,
              99,
              116,
              105,
              118,
              101,
              34,
              125,
              44,
              123,
              34,
              105,
              100,
              34,
              58,
              56,
              51,
              51,
              51,
              49,
              53,
              56,
              44,
              34,
              110,
              97,
              109,
              101,
              34,
              58,
              34,
              78,
              105,
              114,
              97,
              110,
              106,
              97,
              110,
              32,
              65,
              99,
              104,
              97,
              114,
              105,
              32,
              73,
              73,
              34,
              44,
              34,
              101,
              109,
              97,
              105,
              108,
              34,
              58,
              34,
              105,
              105,
              95,
              110,
              105,
              114,
              97,
              110,
              106,
              97,
              110,
              95,
              97,
              99,
              104,
              97,
              114,
              105,
              64,
              106,
              97,
              99,
              111,
              98,
              115,
              111,
              110,
              46,
              101,
              120,
              97,
              109,
              112,
              108,
              101,
              34,
              44,
              34,
              103,
              101,
              110,
              100,
              101,
              114,
              34,
              58,
              34,
              109,
              97,
              108,
              101,
              34,
              44,
              34,
              115,
              116,
              97,
              116,
              117,
              115,
              34,
              58,
              34,
              97,
              99,
              116,
              105,
              118,
              101,
              34,
              125,
              44,
              123,
              34,
              105,
              100,
              34,
              58,
              56,
              51,
              51,
              51,
              49,
              53,
              55,
              44,
              34,
              110,
              97,
              109,
              101,
              34,
              58,
              34,
              65,
              100,
              104,
              105,
              114,
              97,
              106,
              32,
              65,
              115,
              97,
              110,
              34,
              44,
              34,
              101,
              109,
              97,
              105,
              108,
              34,
              58,
              34,
              97,
              115,
              97,
              110,
              95,
              97,
              100,
              104,
              105,
              114,
              97,
              106,
              64,
              109,
              105,
              108,
              108,
              101,
              114,
              46,
              101,
              120,
              97,
              109,
              112,
              108,
              101,
              34,
              44,
              34,
              103,
              101,
              110,
              100,
              101,
              114,
              34,
              58,
              34,
              102,
              101,
              109,
              97,
              108,
              101,
              34,
              44,
              34,
              115,
              116,
              97,
              116,
              117,
              115,
              34,
              58,
              34,
              97,
              99,
              116,
              105,
              118,
              101,
              34,
              125,
              44,
              123,
              34,
              105,
              100,
              34,
              58,
              56,
              51,
              51,
              51,
              49,
              53,
              54,
              44,
              34,
              110,
              97,
              109,
              101,
              34,
              58,
              34,
              65,
              97,
              115,
              104,
              114,
              105,
              116,
              104,
              97,
              32,
              77,
              97,
              104,
              97,
              106,
              97,
              110,
              32,
              77,
              68,
              34,
              44,
              34,
              101,
              109,
              97,
              105,
              108,
              34,
              58,
              34,
              109,
              100,
              95,
              109,
              97,
              104,
              97,
              106,
              97,
              110,
              95,
              97,
              97,
              115,
              104,
              114,
              105,
              116,
              104,
              97,
              64,
              114,
              97,
              121,
              110,
              111,
              114,
              45,
              115,
              116,
              114,
              101,
              105,
              99,
              104,
              46,
              101,
              120,
              97,
              109,
              112,
              108,
              101,
              34,
              44,
              34,
              103,
              101,
              110,
              100,
              101,
              114,
              34,
              58,
              34,
              102,
              101,
              109,
              97,
              108,
              101,
              34,
              44,
              34,
              115,
              116,
              97,
              116,
              117,
              115,
              34,
              58,
              34,
              97,
              99,
              116,
              105,
              118,
              101,
              34,
              125,
              93
            ]
          },
          "cookie": [],
          "responseTime": 1063,
          "responseSize": 1212
        },
        "id": "b797491f-99d5-4817-a15d-ad831af6023f",
        "assertions": [
          {
            "assertion": "Status code is 200",
            "skipped": false
          },
          {
            "assertion": "Response time is less than 200ms",
            "skipped": false,
            "error": {
              "name": "AssertionError",
              "index": 1,
              "test": "Response time is less than 200ms",
              "message": "expected 1063 to be below 1000",
              "stack": "AssertionError: expected 1063 to be below 1000\n   at Object.eval sandbox-script.js:2:1)"
            }
          }
        ]
      },
      {
        "cursor": {
          "ref": "ec809870-4531-4bbd-9e06-065066709805",
          "length": 2,
          "cycles": 1,
          "position": 1,
          "iteration": 0,
          "httpRequestId": "0f5885e2-b922-4c07-9a32-952bbd5e4cd0"
        },
        "item": {
          "id": "7e6a3dbc-887f-49c9-925d-6a3054c15f59",
          "name": "2-GetAUserByID",
          "request": {
            "url": {
              "protocol": "https",
              "path": [
                "public",
                "v2",
                "users",
                "8333165"
              ],
              "host": [
                "gorest",
                "co",
                "in"
              ],
              "query": [],
              "variable": []
            },
            "method": "GET"
          },
          "response": [],
          "event": [
            {
              "listen": "test",
              "script": {
                "id": "1684e710-4821-4314-805d-1d815c5787ba",
                "type": "text/javascript",
                "packages": {},
                "exec": [
                  "pm.test(\"Status code is 200\", function () {",
                  "    pm.response.to.have.status(200);",
                  "});",
                  "pm.test(\"Response time is less than 200ms\", function () {",
                  "    pm.expect(pm.response.responseTime).to.be.below(1000);",
                  "});"
                ],
                "_lastExecutionId": "5353e50c-61db-4b98-972a-791cedcfe60c"
              }
            }
          ]
        },
        "request": {
          "url": {
            "protocol": "https",
            "path": [
              "public",
              "v2",
              "users",
              "8333165"
            ],
            "host": [
              "gorest",
              "co",
              "in"
            ],
            "query": [],
            "variable": []
          },
          "header": [
            {
              "key": "User-Agent",
              "value": "PostmanRuntime/7.39.1",
              "system": true
            },
            {
              "key": "Accept",
              "value": "*/*",
              "system": true
            },
            {
              "key": "Cache-Control",
              "value": "no-cache",
              "system": true
            },
            {
              "key": "Postman-Token",
              "value": "cbe881ef-aae2-4563-83ad-b3eb4f405093",
              "system": true
            },
            {
              "key": "Host",
              "value": "gorest.co.in",
              "system": true
            },
            {
              "key": "Accept-Encoding",
              "value": "gzip, deflate, br",
              "system": true
            },
            {
              "key": "Connection",
              "value": "keep-alive",
              "system": true
            }
          ],
          "method": "GET"
        },
        "response": {
          "id": "dac9570f-dec0-4f8a-ae77-8f2057ed5786",
          "status": "OK",
          "code": 200,
          "header": [
            {
              "key": "Date",
              "value": "Sat, 17 Jan 2026 12:34:00 GMT"
            },
            {
              "key": "Content-Type",
              "value": "application/json; charset=utf-8"
            },
            {
              "key": "Transfer-Encoding",
              "value": "chunked"
            },
            {
              "key": "Connection",
              "value": "keep-alive"
            },
            {
              "key": "Cache-Control",
              "value": "max-age=0, private, must-revalidate"
            },
            {
              "key": "etag",
              "value": "W/\"ff7b569f3df84e08ae028a017d970245\""
            },
            {
              "key": "feature-policy",
              "value": "camera 'none'; gyroscope 'none'; microphone 'none'; usb 'none'; fullscreen 'self'"
            },
            {
              "key": "referrer-policy",
              "value": "strict-origin-when-cross-origin"
            },
            {
              "key": "vary",
              "value": "Origin"
            },
            {
              "key": "x-content-type-options",
              "value": "nosniff"
            },
            {
              "key": "x-download-options",
              "value": "noopen"
            },
            {
              "key": "x-frame-options",
              "value": "SAMEORIGIN"
            },
            {
              "key": "x-permitted-cross-domain-policies",
              "value": "none"
            },
            {
              "key": "x-request-id",
              "value": "a65722f7-9b5c-4945-bc67-dfd8e5cff4cd"
            },
            {
              "key": "x-runtime",
              "value": "0.011500"
            },
            {
              "key": "x-xss-protection",
              "value": "0"
            },
            {
              "key": "Nel",
              "value": "{\"report_to\":\"cf-nel\",\"success_fraction\":0.0,\"max_age\":604800}"
            },
            {
              "key": "cf-cache-status",
              "value": "DYNAMIC"
            },
            {
              "key": "Report-To",
              "value": "{\"group\":\"cf-nel\",\"max_age\":604800,\"endpoints\":[{\"url\":\"https://a.nel.cloudflare.com/report/v4?s=XJD53EkJssTtIv0o93tLbI6BNK%2FKpjE3xK4k7t2W7XBlkTjXXhfVyeurzY3S%2F8EgbwxHdyaUixt5WkoElJFsl9nyYE%2BUa0BCAZ4%3D\"}]}"
            },
            {
              "key": "Content-Encoding",
              "value": "br"
            },
            {
              "key": "Server",
              "value": "cloudflare"
            },
            {
              "key": "CF-RAY",
              "value": "9bf5e25d993f42d9-PHX"
            },
            {
              "key": "alt-svc",
              "value": "h3=\":443\"; ma=86400"
            }
          ],
          "stream": {
            "type": "Buffer",
            "data": [
              123,
              34,
              105,
              100,
              34,
              58,
              56,
              51,
              51,
              51,
              49,
              54,
              53,
              44,
              34,
              110,
              97,
              109,
              101,
              34,
              58,
              34,
              66,
              104,
              97,
              114,
              100,
              119,
              97,
              106,
              32,
              65,
              100,
              105,
              103,
              97,
              34,
              44,
              34,
              101,
              109,
              97,
              105,
              108,
              34,
              58,
              34,
              98,
              104,
              97,
              114,
              100,
              119,
              97,
              106,
              95,
              97,
              100,
              105,
              103,
              97,
              64,
              119,
              97,
              108,
              116,
              101,
              114,
              46,
              116,
              101,
              115,
              116,
              34,
              44,
              34,
              103,
              101,
              110,
              100,
              101,
              114,
              34,
              58,
              34,
              109,
              97,
              108,
              101,
              34,
              44,
              34,
              115,
              116,
              97,
              116,
              117,
              115,
              34,
              58,
              34,
              97,
              99,
              116,
              105,
              118,
              101,
              34,
              125
            ]
          },
          "cookie": [],
          "responseTime": 363,
          "responseSize": 109
        },
        "id": "7e6a3dbc-887f-49c9-925d-6a3054c15f59",
        "assertions": [
          {
            "assertion": "Status code is 200",
            "skipped": false
          },
          {
            "assertion": "Response time is less than 200ms",
            "skipped": false
          }
        ]
      }
    ],
    "transfers": {
      "responseTotal": 1321
    },
    "failures": [
      {
        "error": {
          "name": "AssertionError",
          "index": 1,
          "test": "Response time is less than 200ms",
          "message": "expected 1063 to be below 1000",
          "stack": "AssertionError: expected 1063 to be below 1000\n   at Object.eval sandbox-script.js:2:1)",
          "checksum": "d73970a4988176691540ada5a4387d7b",
          "id": "7c2516a1-acaa-4e66-97ec-f9b7d33eb23f",
          "timestamp": 1768653239903,
          "stacktrace": [
            {
              "fileName": "sandbox-script.js",
              "lineNumber": 2,
              "functionName": "Object.eval",
              "typeName": "Object",
              "methodName": "eval",
              "columnNumber": 1,
              "native": false
            }
          ]
        },
        "at": "assertion:1 in test-script",
        "source": {
          "id": "b797491f-99d5-4817-a15d-ad831af6023f",
          "name": "1-GetAllUsers",
          "request": {
            "url": {
              "protocol": "https",
              "path": [
                "public",
                "v2",
                "users"
              ],
              "host": [
                "gorest",
                "co",
                "in"
              ],
              "query": [],
              "variable": []
            },
            "method": "GET"
          },
          "response": [],
          "event": [
            {
              "listen": "test",
              "script": {
                "id": "be857fda-b0ff-41a8-9fcb-f3712d9a47d0",
                "type": "text/javascript",
                "packages": {},
                "exec": [
                  "pm.test(\"Status code is 200\", function () {",
                  "    pm.response.to.have.status(200);",
                  "});",
                  "pm.test(\"Response time is less than 200ms\", function () {",
                  "    pm.expect(pm.response.responseTime).to.be.below(1000);",
                  "});"
                ],
                "_lastExecutionId": "e145b559-052b-42b6-8afb-a5646becb7b8"
              }
            }
          ]
        },
        "parent": {
          "_": {
            "postman_id": "7574a522-714e-41c6-a22d-8682669221f7",
            "exporter_id": "50807239",
            "collection_link": "https://go.postman.co/collection/50807239-7574a522-714e-41c6-a22d-8682669221f7?source=collection_link"
          },
          "item": [
            {
              "id": "b797491f-99d5-4817-a15d-ad831af6023f",
              "name": "1-GetAllUsers",
              "request": {
                "url": {
                  "protocol": "https",
                  "path": [
                    "public",
                    "v2",
                    "users"
                  ],
                  "host": [
                    "gorest",
                    "co",
                    "in"
                  ],
                  "query": [],
                  "variable": []
                },
                "method": "GET"
              },
              "response": [],
              "event": [
                {
                  "listen": "test",
                  "script": {
                    "id": "be857fda-b0ff-41a8-9fcb-f3712d9a47d0",
                    "type": "text/javascript",
                    "packages": {},
                    "exec": [
                      "pm.test(\"Status code is 200\", function () {",
                      "    pm.response.to.have.status(200);",
                      "});",
                      "pm.test(\"Response time is less than 200ms\", function () {",
                      "    pm.expect(pm.response.responseTime).to.be.below(1000);",
                      "});"
                    ],
                    "_lastExecutionId": "e145b559-052b-42b6-8afb-a5646becb7b8"
                  }
                }
              ]
            },
            {
              "id": "7e6a3dbc-887f-49c9-925d-6a3054c15f59",
              "name": "2-GetAUserByID",
              "request": {
                "url": {
                  "protocol": "https",
                  "path": [
                    "public",
                    "v2",
                    "users",
                    "8333165"
                  ],
                  "host": [
                    "gorest",
                    "co",
                    "in"
                  ],
                  "query": [],
                  "variable": []
                },
                "method": "GET"
              },
              "response": [],
              "event": [
                {
                  "listen": "test",
                  "script": {
                    "id": "1684e710-4821-4314-805d-1d815c5787ba",
                    "type": "text/javascript",
                    "packages": {},
                    "exec": [
                      "pm.test(\"Status code is 200\", function () {",
                      "    pm.response.to.have.status(200);",
                      "});",
                      "pm.test(\"Response time is less than 200ms\", function () {",
                      "    pm.expect(pm.response.responseTime).to.be.below(1000);",
                      "});"
                    ],
                    "_lastExecutionId": "5353e50c-61db-4b98-972a-791cedcfe60c"
                  }
                }
              ]
            }
          ],
          "event": [],
          "variable": [],
          "info": {
            "_postman_id": "7574a522-714e-41c6-a22d-8682669221f7",
            "name": "SimpleCollection",
            "schema": "https://schema.getpostman.com/json/collection/v2.1.0/collection.json"
          }
        },
        "cursor": {
          "position": 0,
          "iteration": 0,
          "length": 2,
          "cycles": 1,
          "empty": false,
          "eof": false,
          "bof": true,
          "cr": false,
          "ref": "439a03cb-bb68-411d-a3d5-12c089f73751",
          "httpRequestId": "22625b35-ffa2-4322-a131-cc62ebd26f80",
          "scriptId": "be857fda-b0ff-41a8-9fcb-f3712d9a47d0",
          "execution": "e145b559-052b-42b6-8afb-a5646becb7b8"
        }
      }
    ],
    "error": null
  }
}