{
  "collection": {
    "_": {
      "postman_id": "a700bad4-cac9-45ae-b774-d07b9b4ef1af",
      "exporter_id": "50807239",
      "collection_link": "https://sathappanas1989-5826752.postman.co/workspace/Jan2025APIWS~2ab078eb-768f-43af-8009-37ca31a1c75a/collection/50807239-a700bad4-cac9-45ae-b774-d07b9b4ef1af?action=share&source=collection_link&creator=50807239"
    },
    "item": [
      {
        "id": "631df186-411b-4947-89e0-609839da154e",
        "name": "1-GetAllUsers",
        "request": {
          "url": {
            "path": [
              "public",
              "v2",
              "users"
            ],
            "host": [
              "{{baseURL}}"
            ],
            "query": [],
            "variable": []
          },
          "header": [
            {
              "key": "Authorization",
              "value": "{{tokenID}}"
            }
          ],
          "method": "GET"
        },
        "response": [],
        "event": [
          {
            "listen": "test",
            "script": {
              "id": "2d071841-9638-4dd4-8e98-39e33fe1b38c",
              "type": "text/javascript",
              "packages": {},
              "exec": [
                "//check the status 200",
                "pm.test(\"Status code is 200\", function () {",
                "    pm.response.to.have.status(200);",
                "});"
              ],
              "_lastExecutionId": "d516ff5c-27ba-4934-9bac-d733aabf9c34"
            }
          }
        ]
      },
      {
        "id": "ff3545c5-a42c-4dd5-aa9b-5dc14d3564ae",
        "name": "2-CreateaUser",
        "request": {
          "url": {
            "path": [
              "public",
              "v2",
              "users",
              ""
            ],
            "host": [
              "{{baseURL}}"
            ],
            "query": [],
            "variable": []
          },
          "header": [
            {
              "key": "Authorization",
              "value": "{{tokenID}}"
            }
          ],
          "method": "POST",
          "body": {
            "mode": "raw",
            "raw": "{\n    \"name\": \"seema\",\n    \"gender\": \"MALE\",\n    \"email\": \"application_{{$randomUserName}}@yahoo.com\",\n    \"status\": \"active\"\n}",
            "options": {
              "raw": {
                "language": "json"
              }
            }
          }
        },
        "response": [],
        "event": [
          {
            "listen": "test",
            "script": {
              "id": "5cc65e2c-a622-41dc-a565-e59d6219787e",
              "type": "text/javascript",
              "packages": {},
              "exec": [
                "const response = pm.response.json();",
                "const user_id = response.id;",
                "console.log(\"userID ===>\" + user_id);",
                "//LDECG",
                "//Setter",
                "pm.variables.set(\"userID\", user_id);",
                "",
                "",
                "//Test Cases:",
                "pm.test(\"Status code is 201\", function () {",
                "    pm.response.to.have.status(201);",
                "});",
                "",
                "pm.test(\"Check your name seema\", function () {",
                "    var jsonData = pm.response.json();",
                "    pm.expect(jsonData.name).to.eql(\"seema\");",
                "});",
                "",
                "pm.test(\"Content-Type is present\", function () {",
                "    pm.response.to.have.header(\"Content-Type\");",
                "});",
                ""
              ],
              "_lastExecutionId": "c1729b08-bfa4-4659-932f-3115a4694e72"
            }
          },
          {
            "listen": "prerequest",
            "script": {
              "id": "3463ae9b-7cd5-4a4a-8c5b-8a8954ca5a04",
              "type": "text/javascript",
              "packages": {},
              "exec": [
                ""
              ],
              "_lastExecutionId": "5d3de0e9-96ba-45a7-8b56-66aa758f1132"
            }
          }
        ]
      },
      {
        "id": "82c89e12-bd64-4f68-8017-a5ebb02a0f22",
        "name": "3-GetAUserID",
        "request": {
          "url": {
            "path": [
              "public",
              "v2",
              "users",
              "{{userID}}"
            ],
            "host": [
              "{{baseURL}}"
            ],
            "query": [],
            "variable": []
          },
          "header": [
            {
              "key": "Authorization",
              "value": "{{tokenID}}"
            }
          ],
          "method": "GET"
        },
        "response": [],
        "event": [
          {
            "listen": "test",
            "script": {
              "id": "fa0333f2-e2ff-4bc5-ac7d-984987034b5c",
              "type": "text/javascript",
              "packages": {},
              "exec": [
                "pm.test(\"Status code is 200\", function () {",
                "    pm.response.to.have.status(200);",
                "});",
                "",
                "pm.test(\"check your id\", function(){",
                "   const newUserID= pm.variables.get(\"userID\"); //getter",
                "   const jsonData=pm.response.json();",
                "   pm.expect(jsonData.id).to.eql(newUserID);",
                "});"
              ],
              "_lastExecutionId": "e21f9db1-46c7-4b92-99d7-33686bcc9098"
            }
          }
        ]
      },
      {
        "id": "bc664dce-c914-462b-9f07-4be408f40e88",
        "name": "4-UpdateAUserByID",
        "request": {
          "url": {
            "path": [
              "public",
              "v2",
              "users",
              "{{userID}}"
            ],
            "host": [
              "{{baseURL}}"
            ],
            "query": [],
            "variable": []
          },
          "header": [
            {
              "key": "Authorization",
              "value": "{{tokenID}}"
            }
          ],
          "method": "PUT",
          "body": {
            "mode": "raw",
            "raw": "{\n    \"status\" : \"inactive\"\n}",
            "options": {
              "raw": {
                "language": "json"
              }
            }
          }
        },
        "response": [],
        "event": [
          {
            "listen": "test",
            "script": {
              "id": "3b82bc8a-4db2-4c8f-bdac-4dc098549888",
              "type": "text/javascript",
              "packages": {},
              "exec": [
                "pm.test(\"Status code is 200\", function () {",
                "    pm.response.to.have.status(200);",
                "});",
                "pm.test(\"Response time is less than 500ms\", function () {",
                "    pm.expect(pm.response.responseTime).to.be.below(500);",
                "});",
                "",
                "pm.test(\"Your test name\", function () {",
                "    var jsonData = pm.response.json();",
                "    pm.expect(jsonData.status).to.eql(\"inactive\");",
                "});"
              ],
              "_lastExecutionId": "8f3a9322-e3a7-4253-bef6-7a598b6e96cc"
            }
          }
        ]
      },
      {
        "id": "2dadfb2a-2fd4-4d4e-934d-c72c53142531",
        "name": "5-DeleteAuserID",
        "request": {
          "url": {
            "path": [
              "public",
              "v2",
              "users",
              "{{userID}}"
            ],
            "host": [
              "{{baseURL}}"
            ],
            "query": [],
            "variable": []
          },
          "header": [
            {
              "key": "Authorization",
              "value": "{{tokenID}}"
            }
          ],
          "method": "DELETE"
        },
        "response": [],
        "event": [
          {
            "listen": "test",
            "script": {
              "id": "1acbfc08-6e62-4814-baeb-793d28ffcd10",
              "type": "text/javascript",
              "packages": {},
              "exec": [
                "pm.test(\"Status code is 204\", function () {",
                "    pm.response.to.have.status(204);",
                "});"
              ],
              "_lastExecutionId": "278d8076-607c-493b-a556-fc4845101aa8"
            }
          }
        ]
      },
      {
        "id": "b5e4d3a5-2e51-4574-8851-6f12f6655d34",
        "name": "6-GetAUserByID",
        "request": {
          "url": {
            "path": [
              "public",
              "v2",
              "users",
              "{{userID}}"
            ],
            "host": [
              "{{baseURL}}"
            ],
            "query": [],
            "variable": []
          },
          "header": [
            {
              "key": "Authorization",
              "value": "{{baseURL}}"
            }
          ],
          "method": "GET"
        },
        "response": [],
        "event": [
          {
            "listen": "test",
            "script": {
              "id": "6fc8bcde-6d05-4ca9-a73c-985e324619ad",
              "type": "text/javascript",
              "packages": {},
              "exec": [
                "pm.test(\"Status code is 404\", function () {",
                "    pm.response.to.have.status(404);",
                "});"
              ],
              "_lastExecutionId": "43c8e811-5efe-423e-923d-d3209d605a21"
            }
          }
        ]
      }
    ],
    "event": [],
    "variable": [],
    "info": {
      "_postman_id": "a700bad4-cac9-45ae-b774-d07b9b4ef1af",
      "name": "GoRestAPIWorkFlow",
      "schema": "https://schema.getpostman.com/json/collection/v2.1.0/collection.json"
    }
  },
  "environment": {
    "_": {
      "postman_variable_scope": "environment",
      "postman_exported_at": "2026-01-14T04:32:39.041Z",
      "postman_exported_using": "Postman/11.80.1"
    },
    "id": "465cf288-f1b9-471a-a8b4-75b64f43e819",
    "name": "GoRestENV",
    "values": [
      {
        "type": "any",
        "value": "https://gorest.co.in",
        "key": "baseURL"
      },
      {
        "type": "any",
        "value": "Bearer 83cae371c84eadfd72651ab2835b9c9c7cb17226f82dfb4850fd76e7edee016e",
        "key": "tokenID"
      }
    ]
  },
  "globals": {
    "id": "aec463c4-1001-4a96-ad73-d175ff74fa56",
    "values": []
  },
  "run": {
    "stats": {
      "iterations": {
        "total": 1,
        "pending": 0,
        "failed": 0
      },
      "items": {
        "total": 6,
        "pending": 0,
        "failed": 0
      },
      "scripts": {
        "total": 7,
        "pending": 0,
        "failed": 0
      },
      "prerequests": {
        "total": 6,
        "pending": 0,
        "failed": 0
      },
      "requests": {
        "total": 6,
        "pending": 0,
        "failed": 0
      },
      "tests": {
        "total": 6,
        "pending": 0,
        "failed": 0
      },
      "assertions": {
        "total": 11,
        "pending": 0,
        "failed": 0
      },
      "testScripts": {
        "total": 6,
        "pending": 0,
        "failed": 0
      },
      "prerequestScripts": {
        "total": 1,
        "pending": 0,
        "failed": 0
      }
    },
    "timings": {
      "responseAverage": 470.5,
      "responseMin": 338,
      "responseMax": 1018,
      "responseSd": 245.2527607727723,
      "dnsAverage": 0,
      "dnsMin": 0,
      "dnsMax": 0,
      "dnsSd": 0,
      "firstByteAverage": 0,
      "firstByteMin": 0,
      "firstByteMax": 0,
      "firstByteSd": 0,
      "started": 1768536500136,
      "completed": 1768536503129
    },
    "executions": [
      {
        "cursor": {
          "position": 0,
          "iteration": 0,
          "length": 6,
          "cycles": 1,
          "empty": false,
          "eof": false,
          "bof": true,
          "cr": false,
          "ref": "dce64e54-ac04-4ee6-8356-c26e2764db68",
          "httpRequestId": "8f03dfbd-b4ec-4333-96b7-7ee8d42c1f1d"
        },
        "item": {
          "id": "631df186-411b-4947-89e0-609839da154e",
          "name": "1-GetAllUsers",
          "request": {
            "url": {
              "path": [
                "public",
                "v2",
                "users"
              ],
              "host": [
                "{{baseURL}}"
              ],
              "query": [],
              "variable": []
            },
            "header": [
              {
                "key": "Authorization",
                "value": "{{tokenID}}"
              }
            ],
            "method": "GET"
          },
          "response": [],
          "event": [
            {
              "listen": "test",
              "script": {
                "id": "2d071841-9638-4dd4-8e98-39e33fe1b38c",
                "type": "text/javascript",
                "packages": {},
                "exec": [
                  "//check the status 200",
                  "pm.test(\"Status code is 200\", function () {",
                  "    pm.response.to.have.status(200);",
                  "});"
                ],
                "_lastExecutionId": "d516ff5c-27ba-4934-9bac-d733aabf9c34"
              }
            }
          ]
        },
        "request": {
          "url": {
            "protocol": "https",
            "path": [
              "public",
              "v2",
              "users"
            ],
            "host": [
              "gorest",
              "co",
              "in"
            ],
            "query": [],
            "variable": []
          },
          "header": [
            {
              "key": "Authorization",
              "value": "Bearer 83cae371c84eadfd72651ab2835b9c9c7cb17226f82dfb4850fd76e7edee016e"
            },
            {
              "key": "User-Agent",
              "value": "PostmanRuntime/7.39.1",
              "system": true
            },
            {
              "key": "Accept",
              "value": "*/*",
              "system": true
            },
            {
              "key": "Cache-Control",
              "value": "no-cache",
              "system": true
            },
            {
              "key": "Postman-Token",
              "value": "09cd8fb8-2d6c-4be1-85cd-7a05a4206fd1",
              "system": true
            },
            {
              "key": "Host",
              "value": "gorest.co.in",
              "system": true
            },
            {
              "key": "Accept-Encoding",
              "value": "gzip, deflate, br",
              "system": true
            },
            {
              "key": "Connection",
              "value": "keep-alive",
              "system": true
            }
          ],
          "method": "GET"
        },
        "response": {
          "id": "dae8fc47-b584-4ab4-bcc5-847c38f6dff7",
          "status": "OK",
          "code": 200,
          "header": [
            {
              "key": "Date",
              "value": "Fri, 16 Jan 2026 04:08:21 GMT"
            },
            {
              "key": "Content-Type",
              "value": "application/json; charset=utf-8"
            },
            {
              "key": "Transfer-Encoding",
              "value": "chunked"
            },
            {
              "key": "Connection",
              "value": "keep-alive"
            },
            {
              "key": "Cache-Control",
              "value": "max-age=0, private, must-revalidate"
            },
            {
              "key": "etag",
              "value": "W/\"be403b305fde6aa666de873c59412f72\""
            },
            {
              "key": "feature-policy",
              "value": "camera 'none'; gyroscope 'none'; microphone 'none'; usb 'none'; fullscreen 'self'"
            },
            {
              "key": "referrer-policy",
              "value": "strict-origin-when-cross-origin"
            },
            {
              "key": "vary",
              "value": "Origin"
            },
            {
              "key": "x-content-type-options",
              "value": "nosniff"
            },
            {
              "key": "x-download-options",
              "value": "noopen"
            },
            {
              "key": "x-frame-options",
              "value": "SAMEORIGIN"
            },
            {
              "key": "x-links-current",
              "value": "https://gorest.co.in/public/v2/users?page=1"
            },
            {
              "key": "x-links-next",
              "value": "https://gorest.co.in/public/v2/users?page=2"
            },
            {
              "key": "x-links-previous",
              "value": ""
            },
            {
              "key": "x-pagination-limit",
              "value": "10"
            },
            {
              "key": "x-pagination-page",
              "value": "1"
            },
            {
              "key": "x-pagination-pages",
              "value": "298"
            },
            {
              "key": "x-pagination-total",
              "value": "2973"
            },
            {
              "key": "x-permitted-cross-domain-policies",
              "value": "none"
            },
            {
              "key": "x-ratelimit-limit",
              "value": "90"
            },
            {
              "key": "x-ratelimit-remaining",
              "value": "86"
            },
            {
              "key": "x-ratelimit-reset",
              "value": "1"
            },
            {
              "key": "x-request-id",
              "value": "4e5d017b-6af6-448d-b4e1-2c086dfcaf59"
            },
            {
              "key": "x-runtime",
              "value": "0.050783"
            },
            {
              "key": "x-xss-protection",
              "value": "0"
            },
            {
              "key": "Nel",
              "value": "{\"report_to\":\"cf-nel\",\"success_fraction\":0.0,\"max_age\":604800}"
            },
            {
              "key": "cf-cache-status",
              "value": "DYNAMIC"
            },
            {
              "key": "Report-To",
              "value": "{\"group\":\"cf-nel\",\"max_age\":604800,\"endpoints\":[{\"url\":\"https://a.nel.cloudflare.com/report/v4?s=L7HjyAHMvAKgrZk2VVaoi0LWWeTTIFE%2FtycYiSn%2FgBOuawU0iDMZ5egOq81%2BTUyvDwdhrSSgKNb8zGt%2FTI9kErQWZiMNTzhPIWs%3D\"}]}"
            },
            {
              "key": "Content-Encoding",
              "value": "br"
            },
            {
              "key": "Server",
              "value": "cloudflare"
            },
            {
              "key": "CF-RAY",
              "value": "9beac046e9bb7244-PHX"
            },
            {
              "key": "alt-svc",
              "value": "h3=\":443\"; ma=86400"
            }
          ],
          "stream": {
            "type": "Buffer",
            "data": [
              91,
              123,
              34,
              105,
              100,
              34,
              58,
              56,
              51,
              51,
              51,
              51,
              49,
              50,
              44,
              34,
              110,
              97,
              109,
              101,
              34,
              58,
              34,
              67,
              104,
              97,
              110,
              100,
              114,
              97,
              110,
              105,
              32,
              77,
              101,
              104,
              114,
              111,
              116,
              114,
              97,
              34,
              44,
              34,
              101,
              109,
              97,
              105,
              108,
              34,
              58,
              34,
              99,
              104,
              97,
              110,
              100,
              114,
              97,
              110,
              105,
              95,
              109,
              101,
              104,
              114,
              111,
              116,
              114,
              97,
              64,
              111,
              107,
              101,
              101,
              102,
              101,
              45,
              109,
              117,
              108,
              108,
              101,
              114,
              46,
              101,
              120,
              97,
              109,
              112,
              108,
              101,
              34,
              44,
              34,
              103,
              101,
              110,
              100,
              101,
              114,
              34,
              58,
              34,
              109,
              97,
              108,
              101,
              34,
              44,
              34,
              115,
              116,
              97,
              116,
              117,
              115,
              34,
              58,
              34,
              97,
              99,
              116,
              105,
              118,
              101,
              34,
              125,
              44,
              123,
              34,
              105,
              100,
              34,
              58,
              56,
              51,
              51,
              51,
              51,
              49,
              49,
              44,
              34,
              110,
              97,
              109,
              101,
              34,
              58,
              34,
              65,
              97,
              100,
              105,
              110,
              97,
              116,
              104,
              32,
              86,
              97,
              114,
              109,
              97,
              110,
              32,
              68,
              86,
              77,
              34,
              44,
              34,
              101,
              109,
              97,
              105,
              108,
              34,
              58,
              34,
              100,
              118,
              109,
              95,
              97,
              97,
              100,
              105,
              110,
              97,
              116,
              104,
              95,
              118,
              97,
              114,
              109,
              97,
              110,
              64,
              98,
              101,
              114,
              103,
              110,
              97,
              117,
              109,
              46,
              116,
              101,
              115,
              116,
              34,
              44,
              34,
              103,
              101,
              110,
              100,
              101,
              114,
              34,
              58,
              34,
              109,
              97,
              108,
              101,
              34,
              44,
              34,
              115,
              116,
              97,
              116,
              117,
              115,
              34,
              58,
              34,
              105,
              110,
              97,
              99,
              116,
              105,
              118,
              101,
              34,
              125,
              44,
              123,
              34,
              105,
              100,
              34,
              58,
              56,
              51,
              51,
              51,
              51,
              49,
              48,
              44,
              34,
              110,
              97,
              109,
              101,
              34,
              58,
              34,
              68,
              101,
              118,
              97,
              110,
              105,
              32,
              78,
              97,
              109,
              98,
              101,
              101,
              115,
              97,
              110,
              34,
              44,
              34,
              101,
              109,
              97,
              105,
              108,
              34,
              58,
              34,
              100,
              101,
              118,
              97,
              110,
              105,
              95,
              110,
              97,
              109,
              98,
              101,
              101,
              115,
              97,
              110,
              64,
              108,
              101,
              109,
              107,
              101,
              45,
              112,
              97,
              99,
              111,
              99,
              104,
              97,
              46,
              101,
              120,
              97,
              109,
              112,
              108,
              101,
              34,
              44,
              34,
              103,
              101,
              110,
              100,
              101,
              114,
              34,
              58,
              34,
              102,
              101,
              109,
              97,
              108,
              101,
              34,
              44,
              34,
              115,
              116,
              97,
              116,
              117,
              115,
              34,
              58,
              34,
              105,
              110,
              97,
              99,
              116,
              105,
              118,
              101,
              34,
              125,
              44,
              123,
              34,
              105,
              100,
              34,
              58,
              56,
              51,
              51,
              51,
              51,
              48,
              57,
              44,
              34,
              110,
              97,
              109,
              101,
              34,
              58,
              34,
              69,
              115,
              104,
              97,
              110,
              97,
              32,
              74,
              111,
              115,
              104,
              105,
              32,
              68,
              68,
              83,
              34,
              44,
              34,
              101,
              109,
              97,
              105,
              108,
              34,
              58,
              34,
              101,
              115,
              104,
              97,
              110,
              97,
              95,
              100,
              100,
              115,
              95,
              106,
              111,
              115,
              104,
              105,
              64,
              109,
              99,
              103,
              108,
              121,
              110,
              110,
              45,
              107,
              117,
              110,
              122,
              101,
              46,
              116,
              101,
              115,
              116,
              34,
              44,
              34,
              103,
              101,
              110,
              100,
              101,
              114,
              34,
              58,
              34,
              109,
              97,
              108,
              101,
              34,
              44,
              34,
              115,
              116,
              97,
              116,
              117,
              115,
              34,
              58,
              34,
              97,
              99,
              116,
              105,
              118,
              101,
              34,
              125,
              44,
              123,
              34,
              105,
              100,
              34,
              58,
              56,
              51,
              51,
              51,
              51,
              48,
              55,
              44,
              34,
              110,
              97,
              109,
              101,
              34,
              58,
              34,
              72,
              101,
              101,
              109,
              97,
              32,
              83,
              101,
              116,
              104,
              105,
              32,
              68,
              68,
              83,
              34,
              44,
              34,
              101,
              109,
              97,
              105,
              108,
              34,
              58,
              34,
              104,
              101,
              101,
              109,
              97,
              95,
              100,
              100,
              115,
              95,
              115,
              101,
              116,
              104,
              105,
              64,
              100,
              105,
              99,
              107,
              105,
              45,
              102,
              101,
              105,
              108,
              46,
              101,
              120,
              97,
              109,
              112,
              108,
              101,
              34,
              44,
              34,
              103,
              101,
              110,
              100,
              101,
              114,
              34,
              58,
              34,
              109,
              97,
              108,
              101,
              34,
              44,
              34,
              115,
              116,
              97,
              116,
              117,
              115,
              34,
              58,
              34,
              97,
              99,
              116,
              105,
              118,
              101,
              34,
              125,
              44,
              123,
              34,
              105,
              100,
              34,
              58,
              56,
              51,
              51,
              51,
              51,
              48,
              54,
              44,
              34,
              110,
              97,
              109,
              101,
              34,
              58,
              34,
              85,
              114,
              109,
              105,
              108,
              97,
              32,
              82,
              97,
              110,
              97,
              34,
              44,
              34,
              101,
              109,
              97,
              105,
              108,
              34,
              58,
              34,
              114,
              97,
              110,
              97,
              95,
              117,
              114,
              109,
              105,
              108,
              97,
              64,
              114,
              111,
              100,
              114,
              105,
              103,
              117,
              101,
              122,
              46,
              101,
              120,
              97,
              109,
              112,
              108,
              101,
              34,
              44,
              34,
              103,
              101,
              110,
              100,
              101,
              114,
              34,
              58,
              34,
              109,
              97,
              108,
              101,
              34,
              44,
              34,
              115,
              116,
              97,
              116,
              117,
              115,
              34,
              58,
              34,
              97,
              99,
              116,
              105,
              118,
              101,
              34,
              125,
              44,
              123,
              34,
              105,
              100,
              34,
              58,
              56,
              51,
              51,
              51,
              51,
              48,
              53,
              44,
              34,
              110,
              97,
              109,
              101,
              34,
              58,
              34,
              86,
              97,
              105,
              115,
              104,
              110,
              111,
              32,
              84,
              114,
              105,
              118,
              101,
              100,
              105,
              34,
              44,
              34,
              101,
              109,
              97,
              105,
              108,
              34,
              58,
              34,
              116,
              114,
              105,
              118,
              101,
              100,
              105,
              95,
              118,
              97,
              105,
              115,
              104,
              110,
              111,
              64,
              108,
              101,
              98,
              115,
              97,
              99,
              107,
              46,
              101,
              120,
              97,
              109,
              112,
              108,
              101,
              34,
              44,
              34,
              103,
              101,
              110,
              100,
              101,
              114,
              34,
              58,
              34,
              109,
              97,
              108,
              101,
              34,
              44,
              34,
              115,
              116,
              97,
              116,
              117,
              115,
              34,
              58,
              34,
              105,
              110,
              97,
              99,
              116,
              105,
              118,
              101,
              34,
              125,
              44,
              123,
              34,
              105,
              100,
              34,
              58,
              56,
              51,
              51,
              51,
              51,
              48,
              52,
              44,
              34,
              110,
              97,
              109,
              101,
              34,
              58,
              34,
              66,
              104,
              97,
              100,
              114,
              97,
              32,
              68,
              119,
              105,
              118,
              101,
              100,
              105,
              34,
              44,
              34,
              101,
              109,
              97,
              105,
              108,
              34,
              58,
              34,
              100,
              119,
              105,
              118,
              101,
              100,
              105,
              95,
              98,
              104,
              97,
              100,
              114,
              97,
              64,
              98,
              101,
              101,
              114,
              45,
              106,
              97,
              99,
              111,
              98,
              105,
              46,
              116,
              101,
              115,
              116,
              34,
              44,
              34,
              103,
              101,
              110,
              100,
              101,
              114,
              34,
              58,
              34,
              102,
              101,
              109,
              97,
              108,
              101,
              34,
              44,
              34,
              115,
              116,
              97,
              116,
              117,
              115,
              34,
              58,
              34,
              97,
              99,
              116,
              105,
              118,
              101,
              34,
              125,
              44,
              123,
              34,
              105,
              100,
              34,
              58,
              56,
              51,
              51,
              51,
              49,
              55,
              51,
              44,
              34,
              110,
              97,
              109,
              101,
              34,
              58,
              34,
              65,
              109,
              105,
              115,
              104,
              32,
              83,
              101,
              116,
              104,
              105,
              34,
              44,
              34,
              101,
              109,
              97,
              105,
              108,
              34,
              58,
              34,
              115,
              101,
              116,
              104,
              105,
              95,
              97,
              109,
              105,
              115,
              104,
              64,
              104,
              111,
              100,
              107,
              105,
              101,
              119,
              105,
              99,
              122,
              46,
              101,
              120,
              97,
              109,
              112,
              108,
              101,
              34,
              44,
              34,
              103,
              101,
              110,
              100,
              101,
              114,
              34,
              58,
              34,
              109,
              97,
              108,
              101,
              34,
              44,
              34,
              115,
              116,
              97,
              116,
              117,
              115,
              34,
              58,
              34,
              97,
              99,
              116,
              105,
              118,
              101,
              34,
              125,
              44,
              123,
              34,
              105,
              100,
              34,
              58,
              56,
              51,
              51,
              51,
              49,
              55,
              50,
              44,
              34,
              110,
              97,
              109,
              101,
              34,
              58,
              34,
              65,
              115,
              104,
              97,
              32,
              80,
              111,
              116,
              104,
              117,
              118,
              97,
              97,
              108,
              34,
              44,
              34,
              101,
              109,
              97,
              105,
              108,
              34,
              58,
              34,
              97,
              115,
              104,
              97,
              95,
              112,
              111,
              116,
              104,
              117,
              118,
              97,
              97,
              108,
              64,
              103,
              114,
              105,
              109,
              101,
              115,
              46,
              116,
              101,
              115,
              116,
              34,
              44,
              34,
              103,
              101,
              110,
              100,
              101,
              114,
              34,
              58,
              34,
              109,
              97,
              108,
              101,
              34,
              44,
              34,
              115,
              116,
              97,
              116,
              117,
              115,
              34,
              58,
              34,
              105,
              110,
              97,
              99,
              116,
              105,
              118,
              101,
              34,
              125,
              93
            ]
          },
          "cookie": [],
          "responseTime": 1018,
          "responseSize": 1189
        },
        "id": "631df186-411b-4947-89e0-609839da154e",
        "assertions": [
          {
            "assertion": "Status code is 200",
            "skipped": false
          }
        ]
      },
      {
        "cursor": {
          "ref": "5d8c0354-144a-4da3-8ec6-1ff29e334d61",
          "length": 6,
          "cycles": 1,
          "position": 1,
          "iteration": 0,
          "httpRequestId": "dc752343-647b-40ba-8aec-4fa93fb9045a"
        },
        "item": {
          "id": "ff3545c5-a42c-4dd5-aa9b-5dc14d3564ae",
          "name": "2-CreateaUser",
          "request": {
            "url": {
              "path": [
                "public",
                "v2",
                "users",
                ""
              ],
              "host": [
                "{{baseURL}}"
              ],
              "query": [],
              "variable": []
            },
            "header": [
              {
                "key": "Authorization",
                "value": "{{tokenID}}"
              }
            ],
            "method": "POST",
            "body": {
              "mode": "raw",
              "raw": "{\n    \"name\": \"seema\",\n    \"gender\": \"MALE\",\n    \"email\": \"application_{{$randomUserName}}@yahoo.com\",\n    \"status\": \"active\"\n}",
              "options": {
                "raw": {
                  "language": "json"
                }
              }
            }
          },
          "response": [],
          "event": [
            {
              "listen": "test",
              "script": {
                "id": "5cc65e2c-a622-41dc-a565-e59d6219787e",
                "type": "text/javascript",
                "packages": {},
                "exec": [
                  "const response = pm.response.json();",
                  "const user_id = response.id;",
                  "console.log(\"userID ===>\" + user_id);",
                  "//LDECG",
                  "//Setter",
                  "pm.variables.set(\"userID\", user_id);",
                  "",
                  "",
                  "//Test Cases:",
                  "pm.test(\"Status code is 201\", function () {",
                  "    pm.response.to.have.status(201);",
                  "});",
                  "",
                  "pm.test(\"Check your name seema\", function () {",
                  "    var jsonData = pm.response.json();",
                  "    pm.expect(jsonData.name).to.eql(\"seema\");",
                  "});",
                  "",
                  "pm.test(\"Content-Type is present\", function () {",
                  "    pm.response.to.have.header(\"Content-Type\");",
                  "});",
                  ""
                ],
                "_lastExecutionId": "c1729b08-bfa4-4659-932f-3115a4694e72"
              }
            },
            {
              "listen": "prerequest",
              "script": {
                "id": "3463ae9b-7cd5-4a4a-8c5b-8a8954ca5a04",
                "type": "text/javascript",
                "packages": {},
                "exec": [
                  ""
                ],
                "_lastExecutionId": "5d3de0e9-96ba-45a7-8b56-66aa758f1132"
              }
            }
          ]
        },
        "request": {
          "url": {
            "protocol": "https",
            "path": [
              "public",
              "v2",
              "users",
              ""
            ],
            "host": [
              "gorest",
              "co",
              "in"
            ],
            "query": [],
            "variable": []
          },
          "header": [
            {
              "key": "Authorization",
              "value": "Bearer 83cae371c84eadfd72651ab2835b9c9c7cb17226f82dfb4850fd76e7edee016e"
            },
            {
              "key": "Content-Type",
              "value": "application/json",
              "system": true
            },
            {
              "key": "User-Agent",
              "value": "PostmanRuntime/7.39.1",
              "system": true
            },
            {
              "key": "Accept",
              "value": "*/*",
              "system": true
            },
            {
              "key": "Cache-Control",
              "value": "no-cache",
              "system": true
            },
            {
              "key": "Postman-Token",
              "value": "24c93508-0b61-41c5-914c-2f167a6a984c",
              "system": true
            },
            {
              "key": "Host",
              "value": "gorest.co.in",
              "system": true
            },
            {
              "key": "Accept-Encoding",
              "value": "gzip, deflate, br",
              "system": true
            },
            {
              "key": "Connection",
              "value": "keep-alive",
              "system": true
            },
            {
              "key": "Content-Length",
              "value": "125",
              "system": true
            }
          ],
          "method": "POST",
          "body": {
            "mode": "raw",
            "raw": "{\n    \"name\": \"seema\",\n    \"gender\": \"MALE\",\n    \"email\": \"application_Marcelo_Streich80@yahoo.com\",\n    \"status\": \"active\"\n}",
            "options": {
              "raw": {
                "language": "json"
              }
            }
          }
        },
        "response": {
          "id": "7e3535b5-3b34-4700-aad8-8b94280125fd",
          "status": "Created",
          "code": 201,
          "header": [
            {
              "key": "Date",
              "value": "Fri, 16 Jan 2026 04:08:21 GMT"
            },
            {
              "key": "Content-Type",
              "value": "application/json; charset=utf-8"
            },
            {
              "key": "Content-Length",
              "value": "113"
            },
            {
              "key": "Connection",
              "value": "keep-alive"
            },
            {
              "key": "Cache-Control",
              "value": "max-age=0, private, must-revalidate"
            },
            {
              "key": "etag",
              "value": "W/\"369bfa91bfd400d50d9480af191988d9\""
            },
            {
              "key": "feature-policy",
              "value": "camera 'none'; gyroscope 'none'; microphone 'none'; usb 'none'; fullscreen 'self'"
            },
            {
              "key": "location",
              "value": "https://gorest.co.in/public/v2/users/8333749"
            },
            {
              "key": "referrer-policy",
              "value": "strict-origin-when-cross-origin"
            },
            {
              "key": "vary",
              "value": "Origin"
            },
            {
              "key": "x-content-type-options",
              "value": "nosniff"
            },
            {
              "key": "x-download-options",
              "value": "noopen"
            },
            {
              "key": "x-frame-options",
              "value": "SAMEORIGIN"
            },
            {
              "key": "x-permitted-cross-domain-policies",
              "value": "none"
            },
            {
              "key": "x-ratelimit-limit",
              "value": "90"
            },
            {
              "key": "x-ratelimit-remaining",
              "value": "89"
            },
            {
              "key": "x-ratelimit-reset",
              "value": "2"
            },
            {
              "key": "x-request-id",
              "value": "21b69181-e715-4140-9852-450e88b7d5a6"
            },
            {
              "key": "x-runtime",
              "value": "0.057438"
            },
            {
              "key": "x-xss-protection",
              "value": "0"
            },
            {
              "key": "Nel",
              "value": "{\"report_to\":\"cf-nel\",\"success_fraction\":0.0,\"max_age\":604800}"
            },
            {
              "key": "cf-cache-status",
              "value": "DYNAMIC"
            },
            {
              "key": "Report-To",
              "value": "{\"group\":\"cf-nel\",\"max_age\":604800,\"endpoints\":[{\"url\":\"https://a.nel.cloudflare.com/report/v4?s=8xCtGaU62ZM2wYxHafQgiQrAzmFr2Wpvy0J3yZO2VOvaTW7w6DXkr%2F6X1zWhQJ2pf7odc%2FQYS1YC3S3%2B9TkGoSLnNEDuy8gQgBI%3D\"}]}"
            },
            {
              "key": "Server",
              "value": "cloudflare"
            },
            {
              "key": "CF-RAY",
              "value": "9beac04ca9e37244-PHX"
            },
            {
              "key": "alt-svc",
              "value": "h3=\":443\"; ma=86400"
            }
          ],
          "stream": {
            "type": "Buffer",
            "data": [
              123,
              34,
              105,
              100,
              34,
              58,
              56,
              51,
              51,
              51,
              55,
              52,
              57,
              44,
              34,
              110,
              97,
              109,
              101,
              34,
              58,
              34,
              115,
              101,
              101,
              109,
              97,
              34,
              44,
              34,
              101,
              109,
              97,
              105,
              108,
              34,
              58,
              34,
              97,
              112,
              112,
              108,
              105,
              99,
              97,
              116,
              105,
              111,
              110,
              95,
              77,
              97,
              114,
              99,
              101,
              108,
              111,
              95,
              83,
              116,
              114,
              101,
              105,
              99,
              104,
              56,
              48,
              64,
              121,
              97,
              104,
              111,
              111,
              46,
              99,
              111,
              109,
              34,
              44,
              34,
              103,
              101,
              110,
              100,
              101,
              114,
              34,
              58,
              34,
              109,
              97,
              108,
              101,
              34,
              44,
              34,
              115,
              116,
              97,
              116,
              117,
              115,
              34,
              58,
              34,
              97,
              99,
              116,
              105,
              118,
              101,
              34,
              125
            ]
          },
          "cookie": [],
          "responseTime": 361,
          "responseSize": 113
        },
        "id": "ff3545c5-a42c-4dd5-aa9b-5dc14d3564ae",
        "assertions": [
          {
            "assertion": "Status code is 201",
            "skipped": false
          },
          {
            "assertion": "Check your name seema",
            "skipped": false
          },
          {
            "assertion": "Content-Type is present",
            "skipped": false
          }
        ]
      },
      {
        "cursor": {
          "ref": "9de95d7b-559e-434c-ac78-07fe200cc782",
          "length": 6,
          "cycles": 1,
          "position": 2,
          "iteration": 0,
          "httpRequestId": "c3a87b12-35ca-4907-81b7-c12e0ddc2695"
        },
        "item": {
          "id": "82c89e12-bd64-4f68-8017-a5ebb02a0f22",
          "name": "3-GetAUserID",
          "request": {
            "url": {
              "path": [
                "public",
                "v2",
                "users",
                "{{userID}}"
              ],
              "host": [
                "{{baseURL}}"
              ],
              "query": [],
              "variable": []
            },
            "header": [
              {
                "key": "Authorization",
                "value": "{{tokenID}}"
              }
            ],
            "method": "GET"
          },
          "response": [],
          "event": [
            {
              "listen": "test",
              "script": {
                "id": "fa0333f2-e2ff-4bc5-ac7d-984987034b5c",
                "type": "text/javascript",
                "packages": {},
                "exec": [
                  "pm.test(\"Status code is 200\", function () {",
                  "    pm.response.to.have.status(200);",
                  "});",
                  "",
                  "pm.test(\"check your id\", function(){",
                  "   const newUserID= pm.variables.get(\"userID\"); //getter",
                  "   const jsonData=pm.response.json();",
                  "   pm.expect(jsonData.id).to.eql(newUserID);",
                  "});"
                ],
                "_lastExecutionId": "e21f9db1-46c7-4b92-99d7-33686bcc9098"
              }
            }
          ]
        },
        "request": {
          "url": {
            "protocol": "https",
            "path": [
              "public",
              "v2",
              "users",
              "8333749"
            ],
            "host": [
              "gorest",
              "co",
              "in"
            ],
            "query": [],
            "variable": []
          },
          "header": [
            {
              "key": "Authorization",
              "value": "Bearer 83cae371c84eadfd72651ab2835b9c9c7cb17226f82dfb4850fd76e7edee016e"
            },
            {
              "key": "User-Agent",
              "value": "PostmanRuntime/7.39.1",
              "system": true
            },
            {
              "key": "Accept",
              "value": "*/*",
              "system": true
            },
            {
              "key": "Cache-Control",
              "value": "no-cache",
              "system": true
            },
            {
              "key": "Postman-Token",
              "value": "1b811743-659e-45a4-854c-35737eed070b",
              "system": true
            },
            {
              "key": "Host",
              "value": "gorest.co.in",
              "system": true
            },
            {
              "key": "Accept-Encoding",
              "value": "gzip, deflate, br",
              "system": true
            },
            {
              "key": "Connection",
              "value": "keep-alive",
              "system": true
            }
          ],
          "method": "GET"
        },
        "response": {
          "id": "fd49605a-eaa1-4faa-87b2-a20674fbc6cd",
          "status": "OK",
          "code": 200,
          "header": [
            {
              "key": "Date",
              "value": "Fri, 16 Jan 2026 04:08:21 GMT"
            },
            {
              "key": "Content-Type",
              "value": "application/json; charset=utf-8"
            },
            {
              "key": "Transfer-Encoding",
              "value": "chunked"
            },
            {
              "key": "Connection",
              "value": "keep-alive"
            },
            {
              "key": "Cache-Control",
              "value": "max-age=0, private, must-revalidate"
            },
            {
              "key": "etag",
              "value": "W/\"369bfa91bfd400d50d9480af191988d9\""
            },
            {
              "key": "feature-policy",
              "value": "camera 'none'; gyroscope 'none'; microphone 'none'; usb 'none'; fullscreen 'self'"
            },
            {
              "key": "referrer-policy",
              "value": "strict-origin-when-cross-origin"
            },
            {
              "key": "vary",
              "value": "Origin"
            },
            {
              "key": "x-content-type-options",
              "value": "nosniff"
            },
            {
              "key": "x-download-options",
              "value": "noopen"
            },
            {
              "key": "x-frame-options",
              "value": "SAMEORIGIN"
            },
            {
              "key": "x-permitted-cross-domain-policies",
              "value": "none"
            },
            {
              "key": "x-ratelimit-limit",
              "value": "90"
            },
            {
              "key": "x-ratelimit-remaining",
              "value": "88"
            },
            {
              "key": "x-ratelimit-reset",
              "value": "2"
            },
            {
              "key": "x-request-id",
              "value": "2745676d-2dcf-4a14-91e8-999d4482ba55"
            },
            {
              "key": "x-runtime",
              "value": "0.042175"
            },
            {
              "key": "x-xss-protection",
              "value": "0"
            },
            {
              "key": "Nel",
              "value": "{\"report_to\":\"cf-nel\",\"success_fraction\":0.0,\"max_age\":604800}"
            },
            {
              "key": "cf-cache-status",
              "value": "DYNAMIC"
            },
            {
              "key": "Report-To",
              "value": "{\"group\":\"cf-nel\",\"max_age\":604800,\"endpoints\":[{\"url\":\"https://a.nel.cloudflare.com/report/v4?s=Ns%2FhBVhBcT4bz3JxI3Cx9pIWgjTGEiXJR718Zd%2BVa33J7QlNwbx9IfdFqA%2BdQRfF7pAg%2Fbr%2B0MIk%2FyAEkc3e%2Bb7nWj9IrkfcgAw%3D\"}]}"
            },
            {
              "key": "Content-Encoding",
              "value": "br"
            },
            {
              "key": "Server",
              "value": "cloudflare"
            },
            {
              "key": "CF-RAY",
              "value": "9beac04f18257244-PHX"
            },
            {
              "key": "alt-svc",
              "value": "h3=\":443\"; ma=86400"
            }
          ],
          "stream": {
            "type": "Buffer",
            "data": [
              123,
              34,
              105,
              100,
              34,
              58,
              56,
              51,
              51,
              51,
              55,
              52,
              57,
              44,
              34,
              110,
              97,
              109,
              101,
              34,
              58,
              34,
              115,
              101,
              101,
              109,
              97,
              34,
              44,
              34,
              101,
              109,
              97,
              105,
              108,
              34,
              58,
              34,
              97,
              112,
              112,
              108,
              105,
              99,
              97,
              116,
              105,
              111,
              110,
              95,
              77,
              97,
              114,
              99,
              101,
              108,
              111,
              95,
              83,
              116,
              114,
              101,
              105,
              99,
              104,
              56,
              48,
              64,
              121,
              97,
              104,
              111,
              111,
              46,
              99,
              111,
              109,
              34,
              44,
              34,
              103,
              101,
              110,
              100,
              101,
              114,
              34,
              58,
              34,
              109,
              97,
              108,
              101,
              34,
              44,
              34,
              115,
              116,
              97,
              116,
              117,
              115,
              34,
              58,
              34,
              97,
              99,
              116,
              105,
              118,
              101,
              34,
              125
            ]
          },
          "cookie": [],
          "responseTime": 384,
          "responseSize": 113
        },
        "id": "82c89e12-bd64-4f68-8017-a5ebb02a0f22",
        "assertions": [
          {
            "assertion": "Status code is 200",
            "skipped": false
          },
          {
            "assertion": "check your id",
            "skipped": false
          }
        ]
      },
      {
        "cursor": {
          "ref": "367efa85-003d-4b27-b1a2-8586e9f6ddf8",
          "length": 6,
          "cycles": 1,
          "position": 3,
          "iteration": 0,
          "httpRequestId": "7a6ce8cd-9b55-4569-9c94-bca83ef2ef67"
        },
        "item": {
          "id": "bc664dce-c914-462b-9f07-4be408f40e88",
          "name": "4-UpdateAUserByID",
          "request": {
            "url": {
              "path": [
                "public",
                "v2",
                "users",
                "{{userID}}"
              ],
              "host": [
                "{{baseURL}}"
              ],
              "query": [],
              "variable": []
            },
            "header": [
              {
                "key": "Authorization",
                "value": "{{tokenID}}"
              }
            ],
            "method": "PUT",
            "body": {
              "mode": "raw",
              "raw": "{\n    \"status\" : \"inactive\"\n}",
              "options": {
                "raw": {
                  "language": "json"
                }
              }
            }
          },
          "response": [],
          "event": [
            {
              "listen": "test",
              "script": {
                "id": "3b82bc8a-4db2-4c8f-bdac-4dc098549888",
                "type": "text/javascript",
                "packages": {},
                "exec": [
                  "pm.test(\"Status code is 200\", function () {",
                  "    pm.response.to.have.status(200);",
                  "});",
                  "pm.test(\"Response time is less than 500ms\", function () {",
                  "    pm.expect(pm.response.responseTime).to.be.below(500);",
                  "});",
                  "",
                  "pm.test(\"Your test name\", function () {",
                  "    var jsonData = pm.response.json();",
                  "    pm.expect(jsonData.status).to.eql(\"inactive\");",
                  "});"
                ],
                "_lastExecutionId": "8f3a9322-e3a7-4253-bef6-7a598b6e96cc"
              }
            }
          ]
        },
        "request": {
          "url": {
            "protocol": "https",
            "path": [
              "public",
              "v2",
              "users",
              "8333749"
            ],
            "host": [
              "gorest",
              "co",
              "in"
            ],
            "query": [],
            "variable": []
          },
          "header": [
            {
              "key": "Authorization",
              "value": "Bearer 83cae371c84eadfd72651ab2835b9c9c7cb17226f82dfb4850fd76e7edee016e"
            },
            {
              "key": "Content-Type",
              "value": "application/json",
              "system": true
            },
            {
              "key": "User-Agent",
              "value": "PostmanRuntime/7.39.1",
              "system": true
            },
            {
              "key": "Accept",
              "value": "*/*",
              "system": true
            },
            {
              "key": "Cache-Control",
              "value": "no-cache",
              "system": true
            },
            {
              "key": "Postman-Token",
              "value": "7df29a2d-79f3-4436-a8f6-495435ac7ca6",
              "system": true
            },
            {
              "key": "Host",
              "value": "gorest.co.in",
              "system": true
            },
            {
              "key": "Accept-Encoding",
              "value": "gzip, deflate, br",
              "system": true
            },
            {
              "key": "Connection",
              "value": "keep-alive",
              "system": true
            },
            {
              "key": "Content-Length",
              "value": "29",
              "system": true
            }
          ],
          "method": "PUT",
          "body": {
            "mode": "raw",
            "raw": "{\n    \"status\" : \"inactive\"\n}",
            "options": {
              "raw": {
                "language": "json"
              }
            }
          }
        },
        "response": {
          "id": "e220618b-3364-4e20-a6c1-949ddc948132",
          "status": "OK",
          "code": 200,
          "header": [
            {
              "key": "Date",
              "value": "Fri, 16 Jan 2026 04:08:22 GMT"
            },
            {
              "key": "Content-Type",
              "value": "application/json; charset=utf-8"
            },
            {
              "key": "Transfer-Encoding",
              "value": "chunked"
            },
            {
              "key": "Connection",
              "value": "keep-alive"
            },
            {
              "key": "Cache-Control",
              "value": "max-age=0, private, must-revalidate"
            },
            {
              "key": "etag",
              "value": "W/\"aaaabad9737b6f9a410d9bd656024810\""
            },
            {
              "key": "feature-policy",
              "value": "camera 'none'; gyroscope 'none'; microphone 'none'; usb 'none'; fullscreen 'self'"
            },
            {
              "key": "referrer-policy",
              "value": "strict-origin-when-cross-origin"
            },
            {
              "key": "vary",
              "value": "Origin"
            },
            {
              "key": "x-content-type-options",
              "value": "nosniff"
            },
            {
              "key": "x-download-options",
              "value": "noopen"
            },
            {
              "key": "x-frame-options",
              "value": "SAMEORIGIN"
            },
            {
              "key": "x-permitted-cross-domain-policies",
              "value": "none"
            },
            {
              "key": "x-ratelimit-limit",
              "value": "90"
            },
            {
              "key": "x-ratelimit-remaining",
              "value": "87"
            },
            {
              "key": "x-ratelimit-reset",
              "value": "3"
            },
            {
              "key": "x-request-id",
              "value": "bbb56eea-d311-4799-902e-0b14ce987083"
            },
            {
              "key": "x-runtime",
              "value": "0.046059"
            },
            {
              "key": "x-xss-protection",
              "value": "0"
            },
            {
              "key": "Nel",
              "value": "{\"report_to\":\"cf-nel\",\"success_fraction\":0.0,\"max_age\":604800}"
            },
            {
              "key": "cf-cache-status",
              "value": "DYNAMIC"
            },
            {
              "key": "Report-To",
              "value": "{\"group\":\"cf-nel\",\"max_age\":604800,\"endpoints\":[{\"url\":\"https://a.nel.cloudflare.com/report/v4?s=oMjdMIb0n5Ck80iGmzd6YTVFdMOUo56qP23gfVXJHuHWeTZFQnU0jdJESjxx3TW8D089Ial6%2FVjt2plWiFhNR9BVgV9sOnfdZCY%3D\"}]}"
            },
            {
              "key": "Content-Encoding",
              "value": "br"
            },
            {
              "key": "Server",
              "value": "cloudflare"
            },
            {
              "key": "CF-RAY",
              "value": "9beac051add67244-PHX"
            },
            {
              "key": "alt-svc",
              "value": "h3=\":443\"; ma=86400"
            }
          ],
          "stream": {
            "type": "Buffer",
            "data": [
              123,
              34,
              115,
              116,
              97,
              116,
              117,
              115,
              34,
              58,
              34,
              105,
              110,
              97,
              99,
              116,
              105,
              118,
              101,
              34,
              44,
              34,
              105,
              100,
              34,
              58,
              56,
              51,
              51,
              51,
              55,
              52,
              57,
              44,
              34,
              110,
              97,
              109,
              101,
              34,
              58,
              34,
              115,
              101,
              101,
              109,
              97,
              34,
              44,
              34,
              101,
              109,
              97,
              105,
              108,
              34,
              58,
              34,
              97,
              112,
              112,
              108,
              105,
              99,
              97,
              116,
              105,
              111,
              110,
              95,
              77,
              97,
              114,
              99,
              101,
              108,
              111,
              95,
              83,
              116,
              114,
              101,
              105,
              99,
              104,
              56,
              48,
              64,
              121,
              97,
              104,
              111,
              111,
              46,
              99,
              111,
              109,
              34,
              44,
              34,
              103,
              101,
              110,
              100,
              101,
              114,
              34,
              58,
              34,
              109,
              97,
              108,
              101,
              34,
              125
            ]
          },
          "cookie": [],
          "responseTime": 338,
          "responseSize": 115
        },
        "id": "bc664dce-c914-462b-9f07-4be408f40e88",
        "assertions": [
          {
            "assertion": "Status code is 200",
            "skipped": false
          },
          {
            "assertion": "Response time is less than 500ms",
            "skipped": false
          },
          {
            "assertion": "Your test name",
            "skipped": false
          }
        ]
      },
      {
        "cursor": {
          "ref": "230a1ffa-3cb5-49ad-a7a8-ce3b93b006b2",
          "length": 6,
          "cycles": 1,
          "position": 4,
          "iteration": 0,
          "httpRequestId": "0a775e8f-2953-442d-b280-135fb01b5c5a"
        },
        "item": {
          "id": "2dadfb2a-2fd4-4d4e-934d-c72c53142531",
          "name": "5-DeleteAuserID",
          "request": {
            "url": {
              "path": [
                "public",
                "v2",
                "users",
                "{{userID}}"
              ],
              "host": [
                "{{baseURL}}"
              ],
              "query": [],
              "variable": []
            },
            "header": [
              {
                "key": "Authorization",
                "value": "{{tokenID}}"
              }
            ],
            "method": "DELETE"
          },
          "response": [],
          "event": [
            {
              "listen": "test",
              "script": {
                "id": "1acbfc08-6e62-4814-baeb-793d28ffcd10",
                "type": "text/javascript",
                "packages": {},
                "exec": [
                  "pm.test(\"Status code is 204\", function () {",
                  "    pm.response.to.have.status(204);",
                  "});"
                ],
                "_lastExecutionId": "278d8076-607c-493b-a556-fc4845101aa8"
              }
            }
          ]
        },
        "request": {
          "url": {
            "protocol": "https",
            "path": [
              "public",
              "v2",
              "users",
              "8333749"
            ],
            "host": [
              "gorest",
              "co",
              "in"
            ],
            "query": [],
            "variable": []
          },
          "header": [
            {
              "key": "Authorization",
              "value": "Bearer 83cae371c84eadfd72651ab2835b9c9c7cb17226f82dfb4850fd76e7edee016e"
            },
            {
              "key": "User-Agent",
              "value": "PostmanRuntime/7.39.1",
              "system": true
            },
            {
              "key": "Accept",
              "value": "*/*",
              "system": true
            },
            {
              "key": "Cache-Control",
              "value": "no-cache",
              "system": true
            },
            {
              "key": "Postman-Token",
              "value": "53b0c490-244f-4b7b-91a4-c2c38dd8c25e",
              "system": true
            },
            {
              "key": "Host",
              "value": "gorest.co.in",
              "system": true
            },
            {
              "key": "Accept-Encoding",
              "value": "gzip, deflate, br",
              "system": true
            },
            {
              "key": "Connection",
              "value": "keep-alive",
              "system": true
            }
          ],
          "method": "DELETE"
        },
        "response": {
          "id": "bf37a7cf-bca4-4be4-a891-185f84f75d9e",
          "status": "No Content",
          "code": 204,
          "header": [
            {
              "key": "Date",
              "value": "Fri, 16 Jan 2026 04:08:22 GMT"
            },
            {
              "key": "Connection",
              "value": "keep-alive"
            },
            {
              "key": "Cache-Control",
              "value": "no-cache"
            },
            {
              "key": "feature-policy",
              "value": "camera 'none'; gyroscope 'none'; microphone 'none'; usb 'none'; fullscreen 'self'"
            },
            {
              "key": "referrer-policy",
              "value": "strict-origin-when-cross-origin"
            },
            {
              "key": "vary",
              "value": "Origin"
            },
            {
              "key": "x-content-type-options",
              "value": "nosniff"
            },
            {
              "key": "x-download-options",
              "value": "noopen"
            },
            {
              "key": "x-frame-options",
              "value": "SAMEORIGIN"
            },
            {
              "key": "x-permitted-cross-domain-policies",
              "value": "none"
            },
            {
              "key": "x-ratelimit-limit",
              "value": "90"
            },
            {
              "key": "x-ratelimit-remaining",
              "value": "86"
            },
            {
              "key": "x-ratelimit-reset",
              "value": "4"
            },
            {
              "key": "x-request-id",
              "value": "e74e054c-c6ea-4661-88b5-3860be80da69"
            },
            {
              "key": "x-runtime",
              "value": "0.070132"
            },
            {
              "key": "x-xss-protection",
              "value": "0"
            },
            {
              "key": "cf-cache-status",
              "value": "DYNAMIC"
            },
            {
              "key": "Nel",
              "value": "{\"report_to\":\"cf-nel\",\"success_fraction\":0.0,\"max_age\":604800}"
            },
            {
              "key": "Report-To",
              "value": "{\"group\":\"cf-nel\",\"max_age\":604800,\"endpoints\":[{\"url\":\"https://a.nel.cloudflare.com/report/v4?s=wnDZgLjOBuVnOfv05giMvo3qQzJUssJO%2FbzkiPgZbgOHEHcPyt7sOxmEqFlwgwW5IT1kfmoO4xZeLxaTPaEjncqxgpsqx8ZBqLQ%3D\"}]}"
            },
            {
              "key": "Server",
              "value": "cloudflare"
            },
            {
              "key": "CF-RAY",
              "value": "9beac053f9c27244-PHX"
            },
            {
              "key": "alt-svc",
              "value": "h3=\":443\"; ma=86400"
            }
          ],
          "stream": {
            "type": "Buffer",
            "data": []
          },
          "cookie": [],
          "responseTime": 353,
          "responseSize": 0
        },
        "id": "2dadfb2a-2fd4-4d4e-934d-c72c53142531",
        "assertions": [
          {
            "assertion": "Status code is 204",
            "skipped": false
          }
        ]
      },
      {
        "cursor": {
          "ref": "8d6158c2-8501-4566-8516-a5f1ef98c1d9",
          "length": 6,
          "cycles": 1,
          "position": 5,
          "iteration": 0,
          "httpRequestId": "fa67315a-e585-4bc1-bd1f-e04d59e08550"
        },
        "item": {
          "id": "b5e4d3a5-2e51-4574-8851-6f12f6655d34",
          "name": "6-GetAUserByID",
          "request": {
            "url": {
              "path": [
                "public",
                "v2",
                "users",
                "{{userID}}"
              ],
              "host": [
                "{{baseURL}}"
              ],
              "query": [],
              "variable": []
            },
            "header": [
              {
                "key": "Authorization",
                "value": "{{baseURL}}"
              }
            ],
            "method": "GET"
          },
          "response": [],
          "event": [
            {
              "listen": "test",
              "script": {
                "id": "6fc8bcde-6d05-4ca9-a73c-985e324619ad",
                "type": "text/javascript",
                "packages": {},
                "exec": [
                  "pm.test(\"Status code is 404\", function () {",
                  "    pm.response.to.have.status(404);",
                  "});"
                ],
                "_lastExecutionId": "43c8e811-5efe-423e-923d-d3209d605a21"
              }
            }
          ]
        },
        "request": {
          "url": {
            "protocol": "https",
            "path": [
              "public",
              "v2",
              "users",
              "8333749"
            ],
            "host": [
              "gorest",
              "co",
              "in"
            ],
            "query": [],
            "variable": []
          },
          "header": [
            {
              "key": "Authorization",
              "value": "https://gorest.co.in"
            },
            {
              "key": "User-Agent",
              "value": "PostmanRuntime/7.39.1",
              "system": true
            },
            {
              "key": "Accept",
              "value": "*/*",
              "system": true
            },
            {
              "key": "Cache-Control",
              "value": "no-cache",
              "system": true
            },
            {
              "key": "Postman-Token",
              "value": "76289ed4-dd53-4e40-a170-22d549bc8bfc",
              "system": true
            },
            {
              "key": "Host",
              "value": "gorest.co.in",
              "system": true
            },
            {
              "key": "Accept-Encoding",
              "value": "gzip, deflate, br",
              "system": true
            },
            {
              "key": "Connection",
              "value": "keep-alive",
              "system": true
            }
          ],
          "method": "GET"
        },
        "response": {
          "id": "4dd6b429-026b-47ff-9803-f84e0b7be570",
          "status": "Not Found",
          "code": 404,
          "header": [
            {
              "key": "Date",
              "value": "Fri, 16 Jan 2026 04:08:23 GMT"
            },
            {
              "key": "Content-Type",
              "value": "application/json; charset=utf-8"
            },
            {
              "key": "Transfer-Encoding",
              "value": "chunked"
            },
            {
              "key": "Connection",
              "value": "keep-alive"
            },
            {
              "key": "Cache-Control",
              "value": "no-cache"
            },
            {
              "key": "feature-policy",
              "value": "camera 'none'; gyroscope 'none'; microphone 'none'; usb 'none'; fullscreen 'self'"
            },
            {
              "key": "referrer-policy",
              "value": "strict-origin-when-cross-origin"
            },
            {
              "key": "vary",
              "value": "Origin"
            },
            {
              "key": "x-content-type-options",
              "value": "nosniff"
            },
            {
              "key": "x-download-options",
              "value": "noopen"
            },
            {
              "key": "x-frame-options",
              "value": "SAMEORIGIN"
            },
            {
              "key": "x-permitted-cross-domain-policies",
              "value": "none"
            },
            {
              "key": "x-request-id",
              "value": "65febfd2-12fd-4696-b463-fb1f37c1a423"
            },
            {
              "key": "x-runtime",
              "value": "0.014686"
            },
            {
              "key": "x-xss-protection",
              "value": "0"
            },
            {
              "key": "Nel",
              "value": "{\"report_to\":\"cf-nel\",\"success_fraction\":0.0,\"max_age\":604800}"
            },
            {
              "key": "cf-cache-status",
              "value": "DYNAMIC"
            },
            {
              "key": "Report-To",
              "value": "{\"group\":\"cf-nel\",\"max_age\":604800,\"endpoints\":[{\"url\":\"https://a.nel.cloudflare.com/report/v4?s=FkN4F4LGSEyHHbhj4dtZoprFfDxvBWvQOVaBM%2FxZz7eBKBA2Sfo5%2F5a4kYvTckW95WU%2FMhaO9pGgPp%2BOughKh2tDJU9GPxQb1oE%3D\"}]}"
            },
            {
              "key": "Content-Encoding",
              "value": "br"
            },
            {
              "key": "Server",
              "value": "cloudflare"
            },
            {
              "key": "CF-RAY",
              "value": "9beac0564e0b7244-PHX"
            },
            {
              "key": "alt-svc",
              "value": "h3=\":443\"; ma=86400"
            }
          ],
          "stream": {
            "type": "Buffer",
            "data": [
              123,
              34,
              109,
              101,
              115,
              115,
              97,
              103,
              101,
              34,
              58,
              34,
              82,
              101,
              115,
              111,
              117,
              114,
              99,
              101,
              32,
              110,
              111,
              116,
              32,
              102,
              111,
              117,
              110,
              100,
              34,
              125
            ]
          },
          "cookie": [],
          "responseTime": 369,
          "responseSize": 32
        },
        "id": "b5e4d3a5-2e51-4574-8851-6f12f6655d34",
        "assertions": [
          {
            "assertion": "Status code is 404",
            "skipped": false
          }
        ]
      }
    ],
    "transfers": {
      "responseTotal": 1562
    },
    "failures": [],
    "error": null
  }
}